dephell_markers-1.0.3.dist-info/dependency_links.txt
dephell_markers-1.0.3.dist-info/entry_points.txt
dephell_markers-1.0.3.dist-info/METADATA
dephell_markers-1.0.3.dist-info/top_level.txt
dephell_markers-1.0.3.dist-info/WHEEL
dephell_markers/_cached_property.py
dephell_markers/_constants.py
dephell_markers/__init__.py
dephell_markers/_markers.py
dephell_markers/_operation/_or.py
dephell_markers/_operation/_base.py
dephell_markers/_operation/__init__.py
dephell_markers/_operation/_and.py
dephell_markers/_marker/_version.py
dephell_markers/_marker/_base.py
dephell_markers/_marker/__init__.py
dephell_markers/_marker/_string.py
dephell_markers-1.0.3.dist-info/LICENSE
dephell_markers-1.0.3.dist-info/RECORD