Metadata-Version: 2.1
Name: dephell-markers
Version: 1.0.3
Summary: Work with environment markers (PEP-496)
Project-URL: Repository, https://github.com/dephell/dephell_markers
Author: Gram
Author-email: master_fess@mail.ru
License: MIT
Requires-Python: >=3.5
Keywords: dephell,markers,packaging,versioning
Classifier: Development Status :: 4 - Beta
Classifier: Environment :: Console
Classifier: Intended Audience :: Developers
Classifier: License :: OSI Approved :: MIT License
Classifier: Programming Language :: Python
Classifier: Topic :: Software Development :: Libraries :: Python Modules
Classifier: Topic :: System :: Installation/Setup
Classifier: Programming Language :: Python :: 3.5
Classifier: Programming Language :: Python :: 3.6
Classifier: Programming Language :: Python :: 3.7
Classifier: Programming Language :: Python :: 3.8
Classifier: Programming Language :: Python :: Implementation :: CPython
Classifier: Programming Language :: Python :: Implementation :: PyPy
Classifier: Operating System :: MacOS
Classifier: Operating System :: Microsoft :: Windows
Classifier: Operating System :: Unix
Requires-Dist: attrs
Requires-Dist: dephell-specifier
Requires-Dist: packaging
